venvgen/__init__.py
venvgen/venvgen.py
venvgen/venvgen_version.py
venvgen/OS_control/__init__.py
venvgen/OS_control/macos_system_control.py
venvgen/OS_control/window_system_control.py
venvgen/commands/__init__.py
venvgen/commands/macos_command.py
venvgen/commands/window_command.py
venvgen/general/ANSI_color.py
venvgen/general/ANSI_line_modification.py
venvgen/general/__init__.py
venvgen/general/sha256_generator.py
venvgen/general/string_processing.py
venvgen/general/system_control_protocol.py
venvgen/general/ui_helper.py
venvgen/optionui_modules/__init__.py
venvgen/optionui_modules/option1ui.py
venvgen/optionui_modules/option2ui.py
venvgen/optionui_modules/option3ui.py
venvgen/utils/ANSI_color.py
venvgen/utils/ANSI_line_modification.py
venvgen/utils/__init__.py
venvgen/utils/all_system_control.py
venvgen/utils/check_os.py
venvgen/utils/database_manager.py
venvgen/utils/depedencies_check.py
venvgen/utils/option_manager.py
venvgen/utils/package_directory_manager.py
venvgen/utils/requirement_manager.py
venvgen/utils/sql_command.py
venvgen/utils/string_processing.py
venvgen/utils/system_check.py
venvgen/utils/system_control_protocol.py
venvgen/utils/ui_controler.py
venvgen-2.0.10.dist-info/METADATA
venvgen-2.0.10.dist-info/WHEEL
venvgen-2.0.10.dist-info/entry_points.txt
venvgen-2.0.10.dist-info/top_level.txt
venvgen-2.0.10.dist-info/RECORD
