Metadata-Version: 2.1
Name: venvgen
Version: 2.0.10
Summary: venv Management Software
Requires-Dist: pandas ==2.2.2
Requires-Dist: tabulate ==0.9.0
Requires-Dist: requests
